PythonDanYangbenXuexiShiyongZhinan2021727Fix1Fix1/README.md
PythonDanYangbenXuexiShiyongZhinan2021727Fix1Fix1/__init__.py
PythonDanYangbenXuexiShiyongZhinan2021727Fix1Fix1/__main__.py
PythonDanYangbenXuexiShiyongZhinan2021727Fix1Fix1/file.epub
PythonDanYangbenXuexiShiyongZhinan2021727Fix1Fix1/index.html
PythonDanYangbenXuexiShiyongZhinan2021727Fix1Fix1/css/__init__.py
PythonDanYangbenXuexiShiyongZhinan2021727Fix1Fix1/css/annotations.css
PythonDanYangbenXuexiShiyongZhinan2021727Fix1Fix1/css/main.css
PythonDanYangbenXuexiShiyongZhinan2021727Fix1Fix1/css/normalize.css
PythonDanYangbenXuexiShiyongZhinan2021727Fix1Fix1/css/popup.css
PythonDanYangbenXuexiShiyongZhinan2021727Fix1Fix1/font/__init__.py
PythonDanYangbenXuexiShiyongZhinan2021727Fix1Fix1/font/fontello.eot
PythonDanYangbenXuexiShiyongZhinan2021727Fix1Fix1/font/fontello.svg
PythonDanYangbenXuexiShiyongZhinan2021727Fix1Fix1/font/fontello.ttf
PythonDanYangbenXuexiShiyongZhinan2021727Fix1Fix1/font/fontello.woff
PythonDanYangbenXuexiShiyongZhinan2021727Fix1Fix1/img/__init__.py
PythonDanYangbenXuexiShiyongZhinan2021727Fix1Fix1/img/annotator-glyph-sprite.png
PythonDanYangbenXuexiShiyongZhinan2021727Fix1Fix1/img/annotator-icon-sprite.png
PythonDanYangbenXuexiShiyongZhinan2021727Fix1Fix1/img/apple-touch-icon.png
PythonDanYangbenXuexiShiyongZhinan2021727Fix1Fix1/img/cancelfullscreen.png
PythonDanYangbenXuexiShiyongZhinan2021727Fix1Fix1/img/close.png
PythonDanYangbenXuexiShiyongZhinan2021727Fix1Fix1/img/fullscreen.png
PythonDanYangbenXuexiShiyongZhinan2021727Fix1Fix1/img/loader.gif
PythonDanYangbenXuexiShiyongZhinan2021727Fix1Fix1/img/menu-icon.png
PythonDanYangbenXuexiShiyongZhinan2021727Fix1Fix1/img/save.png
PythonDanYangbenXuexiShiyongZhinan2021727Fix1Fix1/img/saved.png
PythonDanYangbenXuexiShiyongZhinan2021727Fix1Fix1/img/settings-s.png
PythonDanYangbenXuexiShiyongZhinan2021727Fix1Fix1/img/settings.png
PythonDanYangbenXuexiShiyongZhinan2021727Fix1Fix1/img/star.png
python_dan_yangben_xuexi_shiyong_zhinan_2021_7_27_fix1_fix1-2025.3.25.0.dist-info/METADATA
python_dan_yangben_xuexi_shiyong_zhinan_2021_7_27_fix1_fix1-2025.3.25.0.dist-info/WHEEL
python_dan_yangben_xuexi_shiyong_zhinan_2021_7_27_fix1_fix1-2025.3.25.0.dist-info/entry_points.txt
python_dan_yangben_xuexi_shiyong_zhinan_2021_7_27_fix1_fix1-2025.3.25.0.dist-info/top_level.txt
python_dan_yangben_xuexi_shiyong_zhinan_2021_7_27_fix1_fix1-2025.3.25.0.dist-info/RECORD
